{"files":[{"culture":null,"installRoot":null,"ngen":null,"path":"obj\\Debug\\TemplateManifests\\templateManifest0.1033.vstman","targetPath":null,"vsixSubPath":"ProjectTemplates"},{"culture":null,"installRoot":null,"ngen":null,"path":"obj\\Debug\\ProjectTemplates\\Clean Architecture (CQRS)\\1033\\Application\\__TemplateIcon.ico","targetPath":"","vsixSubPath":"ProjectTemplates\\Clean Architecture (CQRS)\\1033\\Application"},{"culture":null,"installRoot":null,"ngen":null,"path":"obj\\Debug\\ProjectTemplates\\Clean Architecture (CQRS)\\1033\\Application\\__TemplateIcon.png","targetPath":"","vsixSubPath":"ProjectTemplates\\Clean Architecture (CQRS)\\1033\\Application"},{"culture":null,"installRoot":null,"ngen":null,"path":"obj\\Debug\\ProjectTemplates\\Clean Architecture (CQRS)\\1033\\Application\\Application.csproj","targetPath":"","vsixSubPath":"ProjectTemplates\\Clean Architecture (CQRS)\\1033\\Application"},{"culture":null,"installRoot":null,"ngen":null,"path":"obj\\Debug\\ProjectTemplates\\Clean Architecture (CQRS)\\1033\\Application\\Common/Interfaces/IApplicationDbContext.cs","targetPath":"","vsixSubPath":"ProjectTemplates\\Clean Architecture (CQRS)\\1033\\Application\\Common\\Interfaces"},{"culture":null,"installRoot":null,"ngen":null,"path":"obj\\Debug\\ProjectTemplates\\Clean Architecture (CQRS)\\1033\\Application\\Common/Interfaces/IIdentityServices.cs","targetPath":"","vsixSubPath":"ProjectTemplates\\Clean Architecture (CQRS)\\1033\\Application\\Common\\Interfaces"},{"culture":null,"installRoot":null,"ngen":null,"path":"obj\\Debug\\ProjectTemplates\\Clean Architecture (CQRS)\\1033\\Application\\Common/Models/Result.cs","targetPath":"","vsixSubPath":"ProjectTemplates\\Clean Architecture (CQRS)\\1033\\Application\\Common\\Models"},{"culture":null,"installRoot":null,"ngen":null,"path":"obj\\Debug\\ProjectTemplates\\Clean Architecture (CQRS)\\1033\\Application\\MyTemplate.vstemplate","targetPath":"","vsixSubPath":"ProjectTemplates\\Clean Architecture (CQRS)\\1033\\Application"},{"culture":null,"installRoot":null,"ngen":null,"path":"obj\\Debug\\ProjectTemplates\\Clean Architecture (CQRS)\\1033\\Application\\Users/Commands/NewUser/NewUserCommand.cs","targetPath":"","vsixSubPath":"ProjectTemplates\\Clean Architecture (CQRS)\\1033\\Application\\Users\\Commands\\NewUser"},{"culture":null,"installRoot":null,"ngen":null,"path":"obj\\Debug\\ProjectTemplates\\Clean Architecture (CQRS)\\1033\\Application\\Users/Commands/NewUser/NewUserCommandHandler.cs","targetPath":"","vsixSubPath":"ProjectTemplates\\Clean Architecture (CQRS)\\1033\\Application\\Users\\Commands\\NewUser"},{"culture":null,"installRoot":null,"ngen":null,"path":"obj\\Debug\\ProjectTemplates\\Clean Architecture (CQRS)\\1033\\Domain\\__TemplateIcon.ico","targetPath":"","vsixSubPath":"ProjectTemplates\\Clean Architecture (CQRS)\\1033\\Domain"},{"culture":null,"installRoot":null,"ngen":null,"path":"obj\\Debug\\ProjectTemplates\\Clean Architecture (CQRS)\\1033\\Domain\\__TemplateIcon.png","targetPath":"","vsixSubPath":"ProjectTemplates\\Clean Architecture (CQRS)\\1033\\Domain"},{"culture":null,"installRoot":null,"ngen":null,"path":"obj\\Debug\\ProjectTemplates\\Clean Architecture (CQRS)\\1033\\Domain\\Common/AuditableEntity.cs","targetPath":"","vsixSubPath":"ProjectTemplates\\Clean Architecture (CQRS)\\1033\\Domain\\Common"},{"culture":null,"installRoot":null,"ngen":null,"path":"obj\\Debug\\ProjectTemplates\\Clean Architecture (CQRS)\\1033\\Domain\\Common/ValueObject.cs","targetPath":"","vsixSubPath":"ProjectTemplates\\Clean Architecture (CQRS)\\1033\\Domain\\Common"},{"culture":null,"installRoot":null,"ngen":null,"path":"obj\\Debug\\ProjectTemplates\\Clean Architecture (CQRS)\\1033\\Domain\\Domain.csproj","targetPath":"","vsixSubPath":"ProjectTemplates\\Clean Architecture (CQRS)\\1033\\Domain"},{"culture":null,"installRoot":null,"ngen":null,"path":"obj\\Debug\\ProjectTemplates\\Clean Architecture (CQRS)\\1033\\Domain\\MyTemplate.vstemplate","targetPath":"","vsixSubPath":"ProjectTemplates\\Clean Architecture (CQRS)\\1033\\Domain"},{"culture":null,"installRoot":null,"ngen":null,"path":"obj\\Debug\\ProjectTemplates\\Clean Architecture (CQRS)\\1033\\Infrastructure\\__TemplateIcon.ico","targetPath":"","vsixSubPath":"ProjectTemplates\\Clean Architecture (CQRS)\\1033\\Infrastructure"},{"culture":null,"installRoot":null,"ngen":null,"path":"obj\\Debug\\ProjectTemplates\\Clean Architecture (CQRS)\\1033\\Infrastructure\\__TemplateIcon.png","targetPath":"","vsixSubPath":"ProjectTemplates\\Clean Architecture (CQRS)\\1033\\Infrastructure"},{"culture":null,"installRoot":null,"ngen":null,"path":"obj\\Debug\\ProjectTemplates\\Clean Architecture (CQRS)\\1033\\Infrastructure\\DependencyInjections.cs","targetPath":"","vsixSubPath":"ProjectTemplates\\Clean Architecture (CQRS)\\1033\\Infrastructure"},{"culture":null,"installRoot":null,"ngen":null,"path":"obj\\Debug\\ProjectTemplates\\Clean Architecture (CQRS)\\1033\\Infrastructure\\Infrastructure.csproj","targetPath":"","vsixSubPath":"ProjectTemplates\\Clean Architecture (CQRS)\\1033\\Infrastructure"},{"culture":null,"installRoot":null,"ngen":null,"path":"obj\\Debug\\ProjectTemplates\\Clean Architecture (CQRS)\\1033\\Infrastructure\\MyTemplate.vstemplate","targetPath":"","vsixSubPath":"ProjectTemplates\\Clean Architecture (CQRS)\\1033\\Infrastructure"},{"culture":null,"installRoot":null,"ngen":null,"path":"obj\\Debug\\ProjectTemplates\\Clean Architecture (CQRS)\\1033\\Infrastructure\\Services/Identity/ApplicationUser.cs","targetPath":"","vsixSubPath":"ProjectTemplates\\Clean Architecture (CQRS)\\1033\\Infrastructure\\Services\\Identity"},{"culture":null,"installRoot":null,"ngen":null,"path":"obj\\Debug\\ProjectTemplates\\Clean Architecture (CQRS)\\1033\\Infrastructure\\Services/Identity/IdentityExtensionMethods.cs","targetPath":"","vsixSubPath":"ProjectTemplates\\Clean Architecture (CQRS)\\1033\\Infrastructure\\Services\\Identity"},{"culture":null,"installRoot":null,"ngen":null,"path":"obj\\Debug\\ProjectTemplates\\Clean Architecture (CQRS)\\1033\\Infrastructure\\Services/Identity/IdentityService.cs","targetPath":"","vsixSubPath":"ProjectTemplates\\Clean Architecture (CQRS)\\1033\\Infrastructure\\Services\\Identity"},{"culture":null,"installRoot":null,"ngen":null,"path":"obj\\Debug\\ProjectTemplates\\Clean Architecture (CQRS)\\1033\\Web UI (.NET 5) Template\\__TemplateIcon.png","targetPath":"","vsixSubPath":"ProjectTemplates\\Clean Architecture (CQRS)\\1033\\Web UI (.NET 5) Template"},{"culture":null,"installRoot":null,"ngen":null,"path":"obj\\Debug\\ProjectTemplates\\Clean Architecture (CQRS)\\1033\\Web UI (.NET 5) Template\\appsettings.Development.json","targetPath":"","vsixSubPath":"ProjectTemplates\\Clean Architecture (CQRS)\\1033\\Web UI (.NET 5) Template"},{"culture":null,"installRoot":null,"ngen":null,"path":"obj\\Debug\\ProjectTemplates\\Clean Architecture (CQRS)\\1033\\Web UI (.NET 5) Template\\appsettings.json","targetPath":"","vsixSubPath":"ProjectTemplates\\Clean Architecture (CQRS)\\1033\\Web UI (.NET 5) Template"},{"culture":null,"installRoot":null,"ngen":null,"path":"obj\\Debug\\ProjectTemplates\\Clean Architecture (CQRS)\\1033\\Web UI (.NET 5) Template\\Controllers/Api/MediatorApiController.cs","targetPath":"","vsixSubPath":"ProjectTemplates\\Clean Architecture (CQRS)\\1033\\Web UI (.NET 5) Template\\Controllers\\Api"},{"culture":null,"installRoot":null,"ngen":null,"path":"obj\\Debug\\ProjectTemplates\\Clean Architecture (CQRS)\\1033\\Web UI (.NET 5) Template\\Controllers/HomeController.cs","targetPath":"","vsixSubPath":"ProjectTemplates\\Clean Architecture (CQRS)\\1033\\Web UI (.NET 5) Template\\Controllers"},{"culture":null,"installRoot":null,"ngen":null,"path":"obj\\Debug\\ProjectTemplates\\Clean Architecture (CQRS)\\1033\\Web UI (.NET 5) Template\\Controllers/LoginController.cs","targetPath":"","vsixSubPath":"ProjectTemplates\\Clean Architecture (CQRS)\\1033\\Web UI (.NET 5) Template\\Controllers"},{"culture":null,"installRoot":null,"ngen":null,"path":"obj\\Debug\\ProjectTemplates\\Clean Architecture (CQRS)\\1033\\Web UI (.NET 5) Template\\Models/ErrorViewModel.cs","targetPath":"","vsixSubPath":"ProjectTemplates\\Clean Architecture (CQRS)\\1033\\Web UI (.NET 5) Template\\Models"},{"culture":null,"installRoot":null,"ngen":null,"path":"obj\\Debug\\ProjectTemplates\\Clean Architecture (CQRS)\\1033\\Web UI (.NET 5) Template\\MyTemplate.vstemplate","targetPath":"","vsixSubPath":"ProjectTemplates\\Clean Architecture (CQRS)\\1033\\Web UI (.NET 5) Template"},{"culture":null,"installRoot":null,"ngen":null,"path":"obj\\Debug\\ProjectTemplates\\Clean Architecture (CQRS)\\1033\\Web UI (.NET 5) Template\\Program.cs","targetPath":"","vsixSubPath":"ProjectTemplates\\Clean Architecture (CQRS)\\1033\\Web UI (.NET 5) Template"},{"culture":null,"installRoot":null,"ngen":null,"path":"obj\\Debug\\ProjectTemplates\\Clean Architecture (CQRS)\\1033\\Web UI (.NET 5) Template\\Properties/launchSettings.json","targetPath":"","vsixSubPath":"ProjectTemplates\\Clean Architecture (CQRS)\\1033\\Web UI (.NET 5) Template\\Properties"},{"culture":null,"installRoot":null,"ngen":null,"path":"obj\\Debug\\ProjectTemplates\\Clean Architecture (CQRS)\\1033\\Web UI (.NET 5) Template\\Startup.cs","targetPath":"","vsixSubPath":"ProjectTemplates\\Clean Architecture (CQRS)\\1033\\Web UI (.NET 5) Template"},{"culture":null,"installRoot":null,"ngen":null,"path":"obj\\Debug\\ProjectTemplates\\Clean Architecture (CQRS)\\1033\\Web UI (.NET 5) Template\\Views/_ViewImports.cshtml","targetPath":"","vsixSubPath":"ProjectTemplates\\Clean Architecture (CQRS)\\1033\\Web UI (.NET 5) Template\\Views"},{"culture":null,"installRoot":null,"ngen":null,"path":"obj\\Debug\\ProjectTemplates\\Clean Architecture (CQRS)\\1033\\Web UI (.NET 5) Template\\Views/_ViewStart.cshtml","targetPath":"","vsixSubPath":"ProjectTemplates\\Clean Architecture (CQRS)\\1033\\Web UI (.NET 5) Template\\Views"},{"culture":null,"installRoot":null,"ngen":null,"path":"obj\\Debug\\ProjectTemplates\\Clean Architecture (CQRS)\\1033\\Web UI (.NET 5) Template\\Views/Home/Index.cshtml","targetPath":"","vsixSubPath":"ProjectTemplates\\Clean Architecture (CQRS)\\1033\\Web UI (.NET 5) Template\\Views\\Home"},{"culture":null,"installRoot":null,"ngen":null,"path":"obj\\Debug\\ProjectTemplates\\Clean Architecture (CQRS)\\1033\\Web UI (.NET 5) Template\\Views/Home/Privacy.cshtml","targetPath":"","vsixSubPath":"ProjectTemplates\\Clean Architecture (CQRS)\\1033\\Web UI (.NET 5) Template\\Views\\Home"},{"culture":null,"installRoot":null,"ngen":null,"path":"obj\\Debug\\ProjectTemplates\\Clean Architecture (CQRS)\\1033\\Web UI (.NET 5) Template\\Views/Home/Register.cshtml","targetPath":"","vsixSubPath":"ProjectTemplates\\Clean Architecture (CQRS)\\1033\\Web UI (.NET 5) Template\\Views\\Home"},{"culture":null,"installRoot":null,"ngen":null,"path":"obj\\Debug\\ProjectTemplates\\Clean Architecture (CQRS)\\1033\\Web UI (.NET 5) Template\\Views/Shared/_Layout.cshtml","targetPath":"","vsixSubPath":"ProjectTemplates\\Clean Architecture (CQRS)\\1033\\Web UI (.NET 5) Template\\Views\\Shared"},{"culture":null,"installRoot":null,"ngen":null,"path":"obj\\Debug\\ProjectTemplates\\Clean Architecture (CQRS)\\1033\\Web UI (.NET 5) Template\\Views/Shared/_ValidationScriptsPartial.cshtml","targetPath":"","vsixSubPath":"ProjectTemplates\\Clean Architecture (CQRS)\\1033\\Web UI (.NET 5) Template\\Views\\Shared"},{"culture":null,"installRoot":null,"ngen":null,"path":"obj\\Debug\\ProjectTemplates\\Clean Architecture (CQRS)\\1033\\Web UI (.NET 5) Template\\Views/Shared/Error.cshtml","targetPath":"","vsixSubPath":"ProjectTemplates\\Clean Architecture (CQRS)\\1033\\Web UI (.NET 5) Template\\Views\\Shared"},{"culture":null,"installRoot":null,"ngen":null,"path":"obj\\Debug\\ProjectTemplates\\Clean Architecture (CQRS)\\1033\\Web UI (.NET 5) Template\\WebCQRSApp1.csproj","targetPath":"","vsixSubPath":"ProjectTemplates\\Clean Architecture (CQRS)\\1033\\Web UI (.NET 5) Template"},{"culture":null,"installRoot":null,"ngen":null,"path":"obj\\Debug\\ProjectTemplates\\Clean Architecture (CQRS)\\1033\\Web UI (.NET 5) Template\\wwwroot/css/site.css","targetPath":"","vsixSubPath":"ProjectTemplates\\Clean Architecture (CQRS)\\1033\\Web UI (.NET 5) Template\\wwwroot\\css"},{"culture":null,"installRoot":null,"ngen":null,"path":"obj\\Debug\\ProjectTemplates\\Clean Architecture (CQRS)\\1033\\Web UI (.NET 5) Template\\wwwroot/favicon.ico","targetPath":"","vsixSubPath":"ProjectTemplates\\Clean Architecture (CQRS)\\1033\\Web UI (.NET 5) Template\\wwwroot"},{"culture":null,"installRoot":null,"ngen":null,"path":"obj\\Debug\\ProjectTemplates\\Clean Architecture (CQRS)\\1033\\Web UI (.NET 5) Template\\wwwroot/js/site.js","targetPath":"","vsixSubPath":"ProjectTemplates\\Clean Architecture (CQRS)\\1033\\Web UI (.NET 5) Template\\wwwroot\\js"},{"culture":null,"installRoot":null,"ngen":null,"path":"obj\\Debug\\ProjectTemplates\\Clean Architecture (CQRS)\\1033\\Web UI (.NET 5) Template\\wwwroot/lib/bootstrap/dist/css/bootstrap.css","targetPath":"","vsixSubPath":"ProjectTemplates\\Clean Architecture (CQRS)\\1033\\Web UI (.NET 5) Template\\wwwroot\\lib\\bootstrap\\dist\\css"},{"culture":null,"installRoot":null,"ngen":null,"path":"obj\\Debug\\ProjectTemplates\\Clean Architecture (CQRS)\\1033\\Web UI (.NET 5) Template\\wwwroot/lib/bootstrap/dist/css/bootstrap.css.map","targetPath":"","vsixSubPath":"ProjectTemplates\\Clean Architecture (CQRS)\\1033\\Web UI (.NET 5) Template\\wwwroot\\lib\\bootstrap\\dist\\css"},{"culture":null,"installRoot":null,"ngen":null,"path":"obj\\Debug\\ProjectTemplates\\Clean Architecture (CQRS)\\1033\\Web UI (.NET 5) Template\\wwwroot/lib/bootstrap/dist/css/bootstrap.min.css","targetPath":"","vsixSubPath":"ProjectTemplates\\Clean Architecture (CQRS)\\1033\\Web UI (.NET 5) Template\\wwwroot\\lib\\bootstrap\\dist\\css"},{"culture":null,"installRoot":null,"ngen":null,"path":"obj\\Debug\\ProjectTemplates\\Clean Architecture (CQRS)\\1033\\Web UI (.NET 5) Template\\wwwroot/lib/bootstrap/dist/css/bootstrap.min.css.map","targetPath":"","vsixSubPath":"ProjectTemplates\\Clean Architecture (CQRS)\\1033\\Web UI (.NET 5) Template\\wwwroot\\lib\\bootstrap\\dist\\css"},{"culture":null,"installRoot":null,"ngen":null,"path":"obj\\Debug\\ProjectTemplates\\Clean Architecture (CQRS)\\1033\\Web UI (.NET 5) Template\\wwwroot/lib/bootstrap/dist/css/bootstrap-grid.css","targetPath":"","vsixSubPath":"ProjectTemplates\\Clean Architecture (CQRS)\\1033\\Web UI (.NET 5) Template\\wwwroot\\lib\\bootstrap\\dist\\css"},{"culture":null,"installRoot":null,"ngen":null,"path":"obj\\Debug\\ProjectTemplates\\Clean Architecture (CQRS)\\1033\\Web UI (.NET 5) Template\\wwwroot/lib/bootstrap/dist/css/bootstrap-grid.css.map","targetPath":"","vsixSubPath":"ProjectTemplates\\Clean Architecture (CQRS)\\1033\\Web UI (.NET 5) Template\\wwwroot\\lib\\bootstrap\\dist\\css"},{"culture":null,"installRoot":null,"ngen":null,"path":"obj\\Debug\\ProjectTemplates\\Clean Architecture (CQRS)\\1033\\Web UI (.NET 5) Template\\wwwroot/lib/bootstrap/dist/css/bootstrap-grid.min.css","targetPath":"","vsixSubPath":"ProjectTemplates\\Clean Architecture (CQRS)\\1033\\Web UI (.NET 5) Template\\wwwroot\\lib\\bootstrap\\dist\\css"},{"culture":null,"installRoot":null,"ngen":null,"path":"obj\\Debug\\ProjectTemplates\\Clean Architecture (CQRS)\\1033\\Web UI (.NET 5) Template\\wwwroot/lib/bootstrap/dist/css/bootstrap-grid.min.css.map","targetPath":"","vsixSubPath":"ProjectTemplates\\Clean Architecture (CQRS)\\1033\\Web UI (.NET 5) Template\\wwwroot\\lib\\bootstrap\\dist\\css"},{"culture":null,"installRoot":null,"ngen":null,"path":"obj\\Debug\\ProjectTemplates\\Clean Architecture (CQRS)\\1033\\Web UI (.NET 5) Template\\wwwroot/lib/bootstrap/dist/css/bootstrap-reboot.css","targetPath":"","vsixSubPath":"ProjectTemplates\\Clean Architecture (CQRS)\\1033\\Web UI (.NET 5) Template\\wwwroot\\lib\\bootstrap\\dist\\css"},{"culture":null,"installRoot":null,"ngen":null,"path":"obj\\Debug\\ProjectTemplates\\Clean Architecture (CQRS)\\1033\\Web UI (.NET 5) Template\\wwwroot/lib/bootstrap/dist/css/bootstrap-reboot.css.map","targetPath":"","vsixSubPath":"ProjectTemplates\\Clean Architecture (CQRS)\\1033\\Web UI (.NET 5) Template\\wwwroot\\lib\\bootstrap\\dist\\css"},{"culture":null,"installRoot":null,"ngen":null,"path":"obj\\Debug\\ProjectTemplates\\Clean Architecture (CQRS)\\1033\\Web UI (.NET 5) Template\\wwwroot/lib/bootstrap/dist/css/bootstrap-reboot.min.css","targetPath":"","vsixSubPath":"ProjectTemplates\\Clean Architecture (CQRS)\\1033\\Web UI (.NET 5) Template\\wwwroot\\lib\\bootstrap\\dist\\css"},{"culture":null,"installRoot":null,"ngen":null,"path":"obj\\Debug\\ProjectTemplates\\Clean Architecture (CQRS)\\1033\\Web UI (.NET 5) Template\\wwwroot/lib/bootstrap/dist/css/bootstrap-reboot.min.css.map","targetPath":"","vsixSubPath":"ProjectTemplates\\Clean Architecture (CQRS)\\1033\\Web UI (.NET 5) Template\\wwwroot\\lib\\bootstrap\\dist\\css"},{"culture":null,"installRoot":null,"ngen":null,"path":"obj\\Debug\\ProjectTemplates\\Clean Architecture (CQRS)\\1033\\Web UI (.NET 5) Template\\wwwroot/lib/bootstrap/dist/js/bootstrap.bundle.js","targetPath":"","vsixSubPath":"ProjectTemplates\\Clean Architecture (CQRS)\\1033\\Web UI (.NET 5) Template\\wwwroot\\lib\\bootstrap\\dist\\js"},{"culture":null,"installRoot":null,"ngen":null,"path":"obj\\Debug\\ProjectTemplates\\Clean Architecture (CQRS)\\1033\\Web UI (.NET 5) Template\\wwwroot/lib/bootstrap/dist/js/bootstrap.bundle.js.map","targetPath":"","vsixSubPath":"ProjectTemplates\\Clean Architecture (CQRS)\\1033\\Web UI (.NET 5) Template\\wwwroot\\lib\\bootstrap\\dist\\js"},{"culture":null,"installRoot":null,"ngen":null,"path":"obj\\Debug\\ProjectTemplates\\Clean Architecture (CQRS)\\1033\\Web UI (.NET 5) Template\\wwwroot/lib/bootstrap/dist/js/bootstrap.bundle.min.js","targetPath":"","vsixSubPath":"ProjectTemplates\\Clean Architecture (CQRS)\\1033\\Web UI (.NET 5) Template\\wwwroot\\lib\\bootstrap\\dist\\js"},{"culture":null,"installRoot":null,"ngen":null,"path":"obj\\Debug\\ProjectTemplates\\Clean Architecture (CQRS)\\1033\\Web UI (.NET 5) Template\\wwwroot/lib/bootstrap/dist/js/bootstrap.bundle.min.js.map","targetPath":"","vsixSubPath":"ProjectTemplates\\Clean Architecture (CQRS)\\1033\\Web UI (.NET 5) Template\\wwwroot\\lib\\bootstrap\\dist\\js"},{"culture":null,"installRoot":null,"ngen":null,"path":"obj\\Debug\\ProjectTemplates\\Clean Architecture (CQRS)\\1033\\Web UI (.NET 5) Template\\wwwroot/lib/bootstrap/dist/js/bootstrap.js","targetPath":"","vsixSubPath":"ProjectTemplates\\Clean Architecture (CQRS)\\1033\\Web UI (.NET 5) Template\\wwwroot\\lib\\bootstrap\\dist\\js"},{"culture":null,"installRoot":null,"ngen":null,"path":"obj\\Debug\\ProjectTemplates\\Clean Architecture (CQRS)\\1033\\Web UI (.NET 5) Template\\wwwroot/lib/bootstrap/dist/js/bootstrap.js.map","targetPath":"","vsixSubPath":"ProjectTemplates\\Clean Architecture (CQRS)\\1033\\Web UI (.NET 5) Template\\wwwroot\\lib\\bootstrap\\dist\\js"},{"culture":null,"installRoot":null,"ngen":null,"path":"obj\\Debug\\ProjectTemplates\\Clean Architecture (CQRS)\\1033\\Web UI (.NET 5) Template\\wwwroot/lib/bootstrap/dist/js/bootstrap.min.js","targetPath":"","vsixSubPath":"ProjectTemplates\\Clean Architecture (CQRS)\\1033\\Web UI (.NET 5) Template\\wwwroot\\lib\\bootstrap\\dist\\js"},{"culture":null,"installRoot":null,"ngen":null,"path":"obj\\Debug\\ProjectTemplates\\Clean Architecture (CQRS)\\1033\\Web UI (.NET 5) Template\\wwwroot/lib/bootstrap/dist/js/bootstrap.min.js.map","targetPath":"","vsixSubPath":"ProjectTemplates\\Clean Architecture (CQRS)\\1033\\Web UI (.NET 5) Template\\wwwroot\\lib\\bootstrap\\dist\\js"},{"culture":null,"installRoot":null,"ngen":null,"path":"obj\\Debug\\ProjectTemplates\\Clean Architecture (CQRS)\\1033\\Web UI (.NET 5) Template\\wwwroot/lib/bootstrap/LICENSE","targetPath":"","vsixSubPath":"ProjectTemplates\\Clean Architecture (CQRS)\\1033\\Web UI (.NET 5) Template\\wwwroot\\lib\\bootstrap"},{"culture":null,"installRoot":null,"ngen":null,"path":"obj\\Debug\\ProjectTemplates\\Clean Architecture (CQRS)\\1033\\Web UI (.NET 5) Template\\wwwroot/lib/jquery/dist/jquery.js","targetPath":"","vsixSubPath":"ProjectTemplates\\Clean Architecture (CQRS)\\1033\\Web UI (.NET 5) Template\\wwwroot\\lib\\jquery\\dist"},{"culture":null,"installRoot":null,"ngen":null,"path":"obj\\Debug\\ProjectTemplates\\Clean Architecture (CQRS)\\1033\\Web UI (.NET 5) Template\\wwwroot/lib/jquery/dist/jquery.min.js","targetPath":"","vsixSubPath":"ProjectTemplates\\Clean Architecture (CQRS)\\1033\\Web UI (.NET 5) Template\\wwwroot\\lib\\jquery\\dist"},{"culture":null,"installRoot":null,"ngen":null,"path":"obj\\Debug\\ProjectTemplates\\Clean Architecture (CQRS)\\1033\\Web UI (.NET 5) Template\\wwwroot/lib/jquery/dist/jquery.min.map","targetPath":"","vsixSubPath":"ProjectTemplates\\Clean Architecture (CQRS)\\1033\\Web UI (.NET 5) Template\\wwwroot\\lib\\jquery\\dist"},{"culture":null,"installRoot":null,"ngen":null,"path":"obj\\Debug\\ProjectTemplates\\Clean Architecture (CQRS)\\1033\\Web UI (.NET 5) Template\\wwwroot/lib/jquery/LICENSE.txt","targetPath":"","vsixSubPath":"ProjectTemplates\\Clean Architecture (CQRS)\\1033\\Web UI (.NET 5) Template\\wwwroot\\lib\\jquery"},{"culture":null,"installRoot":null,"ngen":null,"path":"obj\\Debug\\ProjectTemplates\\Clean Architecture (CQRS)\\1033\\Web UI (.NET 5) Template\\wwwroot/lib/jquery-validation/dist/additional-methods.js","targetPath":"","vsixSubPath":"ProjectTemplates\\Clean Architecture (CQRS)\\1033\\Web UI (.NET 5) Template\\wwwroot\\lib\\jquery-validation\\dist"},{"culture":null,"installRoot":null,"ngen":null,"path":"obj\\Debug\\ProjectTemplates\\Clean Architecture (CQRS)\\1033\\Web UI (.NET 5) Template\\wwwroot/lib/jquery-validation/dist/additional-methods.min.js","targetPath":"","vsixSubPath":"ProjectTemplates\\Clean Architecture (CQRS)\\1033\\Web UI (.NET 5) Template\\wwwroot\\lib\\jquery-validation\\dist"},{"culture":null,"installRoot":null,"ngen":null,"path":"obj\\Debug\\ProjectTemplates\\Clean Architecture (CQRS)\\1033\\Web UI (.NET 5) Template\\wwwroot/lib/jquery-validation/dist/jquery.validate.js","targetPath":"","vsixSubPath":"ProjectTemplates\\Clean Architecture (CQRS)\\1033\\Web UI (.NET 5) Template\\wwwroot\\lib\\jquery-validation\\dist"},{"culture":null,"installRoot":null,"ngen":null,"path":"obj\\Debug\\ProjectTemplates\\Clean Architecture (CQRS)\\1033\\Web UI (.NET 5) Template\\wwwroot/lib/jquery-validation/dist/jquery.validate.min.js","targetPath":"","vsixSubPath":"ProjectTemplates\\Clean Architecture (CQRS)\\1033\\Web UI (.NET 5) Template\\wwwroot\\lib\\jquery-validation\\dist"},{"culture":null,"installRoot":null,"ngen":null,"path":"obj\\Debug\\ProjectTemplates\\Clean Architecture (CQRS)\\1033\\Web UI (.NET 5) Template\\wwwroot/lib/jquery-validation/LICENSE.md","targetPath":"","vsixSubPath":"ProjectTemplates\\Clean Architecture (CQRS)\\1033\\Web UI (.NET 5) Template\\wwwroot\\lib\\jquery-validation"}]}